jk_mediawikiapi/MWAPIException.py
jk_mediawikiapi/MWCategoryInfo.py
jk_mediawikiapi/MWCreatePageResult.py
jk_mediawikiapi/MWExtensionInfo.py
jk_mediawikiapi/MWNamespaceInfo.py
jk_mediawikiapi/MWPage.py
jk_mediawikiapi/MWPageContent.py
jk_mediawikiapi/MWPageInfo.py
jk_mediawikiapi/MWPageRevision.py
jk_mediawikiapi/MWTimestamp.py
jk_mediawikiapi/MWUploadFileResult.py
jk_mediawikiapi/MWUserGroupInfo.py
jk_mediawikiapi/MWUserInfo.py
jk_mediawikiapi/MediaWikiClient.py
jk_mediawikiapi/MediaWikiClient.py.old
jk_mediawikiapi/SMWPropertyInfo.py
jk_mediawikiapi/__init__.py
jk_mediawikiapi/__OLD/_dump.py
jk_mediawikiapi-0.2023.12.10.dist-info/LICENSE.txt
jk_mediawikiapi-0.2023.12.10.dist-info/WHEEL
jk_mediawikiapi-0.2023.12.10.dist-info/METADATA
jk_mediawikiapi-0.2023.12.10.dist-info/RECORD
