Metadata-Version: 2.1
Name: jk_mediawikiapi
Version: 0.2023.12.10
Summary: This python module provides access to a MediaWiki wiki via its API.
Keywords: mediawiki,mediawiki-api
Author-email: Jürgen Knauth <pubsrc@binary-overflow.de>
Requires-Python: >=3.8
Classifier: Development Status :: 4 - Beta
Classifier: Programming Language :: Python
Classifier: Programming Language :: Python :: 3
Classifier: License :: OSI Approved :: Apache Software License
Requires-Dist: jk_furl
Requires-Dist: jk_typing
Requires-Dist: jk_json
Requires-Dist: jk_version
Requires-Dist: jk_prettyprintobj
Requires-Dist: beautifulsoup4
Project-URL: Home, https://github.com/jkpubsrc/python-module-jk-mediawikiapi
Project-URL: Homepage, https://github.com/jkpubsrc/python-module-jk-mediawikiapi
